LICENSE
MANIFEST.in
NEWS
README.rst
setup.cfg
setup.py
giofile/__init__.py
giofile/_main.py
giofile.egg-info/PKG-INFO
giofile.egg-info/SOURCES.txt
giofile.egg-info/dependency_links.txt
giofile.egg-info/requires.txt
giofile.egg-info/top_level.txt
tests/__init__.py
tests/test_main.py