Metadata-Version: 1.1
Name: giofile
Version: 0.2.0
Summary: Opens a Gio.File as a Python file object
Home-page: https://github.com/lazka/giofile
Author: Christoph Reiter
Author-email: reiter.christoph@gmail.com
License: MIT
Platform: UNKNOWN
Classifier: Intended Audience :: Developers
Classifier: License :: OSI Approved :: MIT License
Classifier: Programming Language :: Python :: 2
Classifier: Programming Language :: Python :: 2.7
Classifier: Programming Language :: Python :: 3
Classifier: Programming Language :: Python :: 3.4
Classifier: Programming Language :: Python :: 3.5
Classifier: Programming Language :: Python :: 3.6
Classifier: Programming Language :: Python :: Implementation :: CPython
